querybot/__init__.py
querybot/app.py
querybot/static/index.html
querybot/static/js/script.js
querybot-0.3.3.dist-info/LICENSE
querybot-0.3.3.dist-info/METADATA
querybot-0.3.3.dist-info/WHEEL
querybot-0.3.3.dist-info/entry_points.txt
querybot-0.3.3.dist-info/RECORD
