Metadata-Version: 2.3
Name: querybot
Version: 0.3.3
Summary: A natural language interface for querying datasets using LLMs
License: MIT
Keywords: llm,data,query,chat,sql,duckdb
Author: Prudhvi Krovvidi
Author-email: kprudhvi71@gmail.com
Requires-Python: >=3.10
Classifier: Development Status :: 4 - Beta
Classifier: Environment :: Web Environment
Classifier: Framework :: FastAPI
Classifier: Intended Audience :: Developers
Classifier: License :: OSI Approved :: MIT License
Classifier: Programming Language :: Python :: 3.10
Classifier: Programming Language :: Python :: 3.11
Classifier: Programming Language :: Python :: 3.12
Classifier: Programming Language :: Python :: 3.13
Classifier: Programming Language :: Python :: 3.14
Classifier: Topic :: Database
Classifier: Topic :: Scientific/Engineering :: Artificial Intelligence
Provides-Extra: dev
Requires-Dist: duckdb
Requires-Dist: fastapi
Requires-Dist: httpx
Requires-Dist: numpy
Requires-Dist: pandas
Requires-Dist: platformdirs
Requires-Dist: pydantic
Requires-Dist: pytest ; extra == "dev"
Requires-Dist: pytest-asyncio ; extra == "dev"
Requires-Dist: pytest-cov ; extra == "dev"
Requires-Dist: python-dotenv
Requires-Dist: python-multipart
Requires-Dist: requests
Requires-Dist: ruff ; extra == "dev"
Requires-Dist: uvicorn
Project-URL: Bug Tracker, https://github.com/gramener/querybot/issues
Project-URL: Documentation, https://github.com/gramener/querybot#readme
Project-URL: Homepage, https://github.com/gramener/querybot
Project-URL: Repository, https://github.com/gramener/querybot.git
